Workbook

Sheet PIVOT TABLE
A1: TYPE | B1: Expense
A3: Sum of AMOUNT | B3: MONTH
A4: CATEGORY | B4: Jan | C4: Feb | D4: Mar | E4: Grand Total
A5: EATING OUT | B5: 20000 | C5: 18000 | D5: 36900 | E5: 74900
A6: GROCERIES | B6: 55000 | C6: 53050 | D6: 49000 | E6: 157050
A7: INSURANCE | B7: 20000 | C7: 20000 | D7: 20000 | E7: 60000
A8: Misc | B8: 15000 | C8: 26000 | D8: 16000 | E8: 57000
A9: RENT | B9: 70000 | D9: 70000 | E9: 140000
A10: SAVINGS | B10: 40000 | C10: 40000 | D10: 60000 | E10: 140000
A11: TRANSPORT | B11: 27000 | C11: 26000 | D11: 19000 | E11: 72000
A12: UTILITIES | B12: 48000 | C12: 60000 | D12: 64000 | E12: 172000
A13: Grand Total | B13: 295000 | C13: 243050 | D13: 334900 | E13: 872950

Sheet Raw
A1: DATE | B1: CATEGORY | C1: DESCRIPTION | D1: AMOUNT | E1: TYPE | F1: MONTH
A2: 46024 | B2: RENT | C2: RENT PAYMENT | D2: 70000 | E2: Expense | F2: Jan
A3: 46026 | B3: UTILITIES | C3: ELECTRICITY | D3: 15000 | E3: Expense | F3: Jan
A4: 46026 | B4: UTILITIES | C4: GAS(COOKING) | D4: 8000 | E4: Expense | F4: Jan
A5: 46027 | B5: SALARY | C5: MONTHLY SALARY | D5: 400000 | E5: Income | F5: Jan
A6: 46029 | B6: GROCERIES | C6: GROCERY STORE | D6: 20000 | E6: Expense | F6: Jan
A7: 46030 | B7: UTILITIES | C7: INTERNET | D7: 15000 | E7: Expense | F7: Jan
A8: 46031 | B8: INSURANCE | C8: HEALTH INSURANCE | D8: 12000 | E8: Expense | F8: Jan
A9: 46032 | B9: GROCERIES | C9: GROCERY STORE | D9: 15000 | E9: Expense | F9: Jan
A10: 46034 | B10: TRANSPORT | C10: FUEL(CAR) | D10: 20000 | E10: Expense | F10: Jan
A11: 46037 | B11: GROCERIES | C11: GROCERY STORE | D11: 20000 | E11: Expense | F11: Jan
A12: 46038 | B12: INSURANCE | C12: CAR INSURANCE | D12: 8000 | E12: Expense | F12: Jan
A13: 46038 | B13: EATING OUT | C13: RESTURANT | D13: 10000 | E13: Expense | F13: Jan
... A61: 46105 | B61: INTEREST | C61: BANK INTEREST | D61: 3000 | E61: Income | F61: Mar

Sheet DASHBOARD
A1: MONTHLY SUMMARY
A2: MONTH | B2: TOTAL INCOME | C2: TOTAL EXPENSE | D2: SAVINGS
A3: JAN | B3: =SUMIFS(Raw!D:D,Raw!F:F,"Jan",Raw!E:E,"Income") -> 402000 | C3: =SUMIFS(Raw!D:D,Raw!F:F,"Jan",Raw!E:E,"Expense") -> 295000 | D3: =B3-C3 -> 107000
A4: FEB | B4: =SUMIFS(Raw!D:D,Raw!F:F,"Feb",Raw!E:E,"Income") -> 472000 | C4: =SUMIFS(Raw!D:D,Raw!F:F,"Feb",Raw!E:E,"Expense") -> 243050 | D4: =B4-C4 -> 228950
A5: MAR | B5: =SUMIFS(Raw!D:D,Raw!F:F,"Mar",Raw!E:E,"Income") -> 443000 | C5: =SUMIFS(Raw!D:D,Raw!F:F,"Mar",Raw!E:E,"Expense") -> 334900 | D5: =B5-C5 -> 108100
A6: TOTAL | B6: =SUM(B2:B5) -> 1317000 | C6: =SUM(C2:C5) -> 872950 | D6: =B6-C6 -> 444050
A8: CATEGORY | B8: JAN | C8: FEB | D8: MAR
A9: RENT | B9: =SUMIFS(Raw!D:D,Raw!B:B,"RENT",Raw!F:F,"Jan") -> 70000 | C9: =SUMIFS(Raw!D:D,Raw!B:B,"RENT",Raw!F:F,"Feb") -> 70000 | D9: =SUMIFS(Raw!D:D,Raw!B:B,"RENT",Raw!F:F,"Mar") -> 70000
A10: GROCERIES | B10: =SUMIFS(Raw!D:D,Raw!B:B,"GROCERIES",Raw!F:F,"Jan") -> 55000 | C10: =SUMIFS(Raw!D:D,Raw!B:B,"GROCERIES",Raw!F:F,"Feb") -> 53050 | D10: =SUMIFS(Raw!D:D,Raw!B:B,"GROCERIES",Raw!F:F,"Mar") -> 49000
A11: UTILITIES | B11: =SUMIFS(Raw!D:D,Raw!B:B,"UTILITIES",Raw!F:F,"Jan") -> 48000 | C11: =SUMIFS(Raw!D:D,Raw!B:B,"UTILITIES",Raw!F:F,"Feb") -> 60000 | D11: =SUMIFS(Raw!D:D,Raw!B:B,"UTILITIES",Raw!F:F,"Mar") -> 64000
A12: TRANSPORT | B12: =SUMIFS(Raw!D:D,Raw!B:B,"TRANSPORT",Raw!F:F,"Jan") -> 27000 | C12: =SUMIFS(Raw!D:D,Raw!B:B,"TRANSPORT",Raw!F:F,"Feb") -> 26000 | D12: =SUMIFS(Raw!D:D,Raw!B:B,"TRANSPORT",Raw!F:F,"Mar") -> 19000
A13: GIFT | B13: =SUMIFS(Raw!D:D,Raw!B:B,"GIFT",Raw!F:F,"Jan") -> 0 | C13: =SUMIFS(Raw!D:D,Raw!B:B,"GIFT",Raw!F:F,"Feb") -> 0 | D13: =SUMIFS(Raw!D:D,Raw!B:B,"GIFT",Raw!F:F,"Mar") -> 40000
A14: INSURANCE | B14: =SUMIFS(Raw!D:D,Raw!B:B,"INSURANCE",Raw!F:F,"Jan") -> 20000 | C14: =SUMIFS(Raw!D:D,Raw!B:B,"INSURANCE",Raw!F:F,"Feb") -> 20000 | D14: =SUMIFS(Raw!D:D,Raw!B:B,"INSURANCE",Raw!F:F,"Mar") -> 20000
A15: EATING OUT | B15: =SUMIFS(Raw!D:D,Raw!B:B,"EATING OUT",Raw!F:F,"Jan") -> 20000 | C15: =SUMIFS(Raw!D:D,Raw!B:B,"EATING OUT",Raw!F:F,"Feb") -> 18000 | D15: =SUMIFS(Raw!D:D,Raw!B:B,"EATING OUT",Raw!F:F,"Mar") -> 36900
A16: Misc | B16: =SUMIFS(Raw!D:D,Raw!B:B,"Misc",Raw!F:F,"Jan") -> 15000 | C16: =SUMIFS(Raw!D:D,Raw!B:B,"Misc",Raw!F:F,"Feb") -> 26000 | D16: =SUMIFS(Raw!D:D,Raw!B:B,"Misc",Raw!F:F,"Mar") -> 16000
A17: SAVINGS | B17: =SUMIFS(Raw!D:D,Raw!B:B,"SAVINGS",Raw!F:F,"Jan") -> 40000 | C17: =SUMIFS(Raw!D:D,Raw!B:B,"SAVINGS",Raw!F:F,"Feb") -> 40000 | D17: =SUMIFS(Raw!D:D,Raw!B:B,"savings",Raw!F:F,"Mar") -> 60000
A19: SAINGS SUMMARY
A20: METRIC | B20: VALUE
A21: TOTAL SAVED | B21: =SUM(D3:D5) -> 444050
A22: AVERAGE SAVINGS/MONTH | B22: =AVERAGE(D3:D5) -> 148016.67
A23: BEST MONTH | B23: =MAX(D3:D5) -> 228950
A24: SAVINGS RATE(AVG) | B24: =AVERAGE(D3:D5)/AVERAGE(B3:B5) -> 0.33716781
A25: MONTHS WITH NEGATIVE SAVINGS | B25: =COUNTIF(D3:D5,"<0") -> 0
